{"is_source_file": true, "format": "JavaScript", "description": "This file configures testing utilities for a JavaScript project, specifically adding custom matchers from the '@testing-library/jest-dom' package to extend Jest's assertions for DOM elements.", "external_files": ["@testing-library/jest-dom"], "external_methods": ["expect(element).toHaveTextContent"], "published": ["expect"], "classes": [], "methods": [], "calls": ["import '@testing-library/jest-dom'"], "search-terms": ["setupTests.js", "jest-dom", "testing-library", "custom jest matchers", "test setup"], "state": 2, "file_id": 5, "knowledge_revision": 22, "git_revision": "107d61fe10465288fd60e812f585281968f68478", "ctags": [], "hash": "1a77571e1a8cf36018a41bcedf60db75", "format-version": 4, "code-base-name": "AIPoweredBlogGeneratorMonolith", "filename": "AIPoweredBlogGeneratorMonolith/src/setupTests.js", "revision_history": [{"22": "107d61fe10465288fd60e812f585281968f68478"}]}